{"is_source_file": true, "format": "TypeScript / TSX", "description": "This file defines a React functional component 'Footer' which renders a website footer containing company information, product links, company links, legal links, and copyright information.", "external_files": [], "external_methods": [], "published": [], "classes": [], "methods": [{"name": "Footer", "description": "React functional component rendering the footer section of a webpage."}], "calls": ["React.createElement", "new Date()"], "search-terms": ["Footer", "React functional component", "website footer", "company info", "tailwind classes"], "state": 2, "file_id": 23, "knowledge_revision": 59, "git_revision": "", "ctags": [], "hash": "5f8f987a21621ea29970e63f3f5ae068", "format-version": 4, "code-base-name": "frontend_marketing_site", "filename": "frontend_marketing_site/app/components/Footer.tsx", "revision_history": [{"59": ""}]}