{"is_source_file": true, "format": "TypeScript (TSX)", "description": "A React component implementing a contact form with client-side validation and simulated submission, including form input validation, error handling, and success feedback.", "external_files": ["react"], "external_methods": ["useState"], "published": ["default"], "classes": [], "methods": [{"name": "ContactForm", "description": "Main React functional component rendering the contact form, handling state and submission logic."}, {"name": "onSubmit", "description": "Handler function invoked on form submission; performs validation and manages form state."}, {"name": "Input", "description": "Inner functional component for rendering labeled input fields with validation display."}], "calls": ["React.useState", "setSubmitted", "setErrors", "e.preventDefault", "new FormData", "String", "setTimeout", "e.currentTarget.reset"], "search-terms": ["ContactForm", "client validation", "fake submission", "React form handling", "useState in React", "Formik alternative", "form validation in React"], "state": 2, "file_id": 22, "knowledge_revision": 57, "git_revision": "", "ctags": [], "hash": "1453e254f0546da21fbe07944afe50ed", "format-version": 4, "code-base-name": "frontend_marketing_site", "filename": "frontend_marketing_site/app/components/ContactForm.tsx", "revision_history": [{"57": ""}]}